trim_hwc_ndarray.py
trim_hwc_ndarray-0.1.0a0.dist-info/licenses/LICENSE
trim_hwc_ndarray-0.1.0a0.dist-info/METADATA
trim_hwc_ndarray-0.1.0a0.dist-info/WHEEL
trim_hwc_ndarray-0.1.0a0.dist-info/top_level.txt
trim_hwc_ndarray-0.1.0a0.dist-info/RECORD
