Metadata-Version: 2.4
Name: trim-hwc-ndarray
Version: 0.1.0a0
Summary: A simple utility for trimming borders from images represented as HWC ndarrays, based on the color value of a specified corner.
Author-email: Jifeng Wu <jifengwu2k@gmail.com>
License-Expression: MIT
Project-URL: Homepage, https://github.com/jifengwu2k/trim-hwc-ndarray
Project-URL: Bug Tracker, https://github.com/jifengwu2k/trim-hwc-ndarray/issues
Classifier: Programming Language :: Python :: 2
Classifier: Programming Language :: Python :: 3
Classifier: Operating System :: OS Independent
Requires-Python: >=2
License-File: LICENSE
Requires-Dist: enum34; python_version < "3.4"
Requires-Dist: numpy
Dynamic: license-file
